[
    {
        "Username": null,
        "TrialNumber": 1,
        "EyeCondition": "Left",
        "CorrectOption": "D",
        "GuessedOption": "D",
        "LogMAR": 0.0,
        "Eccentricity_d": 0.0,
        "Theta_d": 0.0,
        "LetterSize_m": 0.0,
        "LogDVA": 0.0,
        "DVA": 0.0,
        "ContrastAlpha_rgb": 255.0,
        "Alpha1": 255.0,
        "Alpha2": 255.0,
        "Ratio": 0.0,
        "LogLum": 0.0,
        "IPD": 0,
        "TimeTakenToGuess_s": 2.924388,
        "Timestamp": "2024-11-23T15:33:57.66689+04:00",
        "TestType": "Contrast"
    },
    {
        "Username": null,
        "TrialNumber": 2,
        "EyeCondition": "Both",
        "CorrectOption": "H",
        "GuessedOption": "H",
        "LogMAR": 0.0,
        "Eccentricity_d": 0.0,
        "Theta_d": 0.0,
        "LetterSize_m": 0.0,
        "LogDVA": 0.0,
        "DVA": 0.0,
        "ContrastAlpha_rgb": 255.0,
        "Alpha1": 255.0,
        "Alpha2": 255.0,
        "Ratio": 0.0,
        "LogLum": 0.0,
        "IPD": 0,
        "TimeTakenToGuess_s": 3.160927,
        "Timestamp": "2024-11-23T15:34:02.317319+04:00",
        "TestType": "Contrast"
    },
    {
        "Username": null,
        "TrialNumber": 3,
        "EyeCondition": "Left",
        "CorrectOption": "D",
        "GuessedOption": "D",
        "LogMAR": 0.0,
        "Eccentricity_d": 0.0,
        "Theta_d": 0.0,
        "LetterSize_m": 0.0,
        "LogDVA": 0.0,
        "DVA": 0.0,
        "ContrastAlpha_rgb": 160.65,
        "Alpha1": 161.0,
        "Alpha2": 160.0,
        "Ratio": 0.65,
        "LogLum": 0.20065945054641829,
        "IPD": 0,
        "TimeTakenToGuess_s": 2.812083,
        "Timestamp": "2024-11-23T15:34:07.273848+04:00",
        "TestType": "Contrast"
    },
    {
        "Username": null,
        "TrialNumber": 4,
        "EyeCondition": "Left",
        "CorrectOption": "Z",
        "GuessedOption": "Z",
        "LogMAR": 0.0,
        "Eccentricity_d": 0.0,
        "Theta_d": 0.0,
        "LetterSize_m": 0.0,
        "LogDVA": 0.0,
        "DVA": 0.0,
        "ContrastAlpha_rgb": 101.2095,
        "Alpha1": 102.0,
        "Alpha2": 101.0,
        "Ratio": 0.21,
        "LogLum": 0.40131890109283658,
        "IPD": 0,
        "TimeTakenToGuess_s": 3.188298,
        "Timestamp": "2024-11-23T15:34:12.508847+04:00",
        "TestType": "Contrast"
    },
    {
        "Username": null,
        "TrialNumber": 5,
        "EyeCondition": "Both",
        "CorrectOption": "N",
        "GuessedOption": "N",
        "LogMAR": 0.0,
        "Eccentricity_d": 0.0,
        "Theta_d": 0.0,
        "LetterSize_m": 0.0,
        "LogDVA": 0.0,
        "DVA": 0.0,
        "ContrastAlpha_rgb": 160.65,
        "Alpha1": 161.0,
        "Alpha2": 160.0,
        "Ratio": 0.65,
        "LogLum": 0.20065945054641829,
        "IPD": 0,
        "TimeTakenToGuess_s": 2.812496,
        "Timestamp": "2024-11-23T15:34:18.077666+04:00",
        "TestType": "Contrast"
    },
    {
        "Username": null,
        "TrialNumber": 6,
        "EyeCondition": "Right",
        "CorrectOption": "O",
        "GuessedOption": "O",
        "LogMAR": 0.0,
        "Eccentricity_d": 0.0,
        "Theta_d": 0.0,
        "LetterSize_m": 0.0,
        "LogDVA": 0.0,
        "DVA": 0.0,
        "ContrastAlpha_rgb": 255.0,
        "Alpha1": 255.0,
        "Alpha2": 255.0,
        "Ratio": 0.0,
        "LogLum": 0.0,
        "IPD": 0,
        "TimeTakenToGuess_s": 3.411365,
        "Timestamp": "2024-11-23T15:34:23.006054+04:00",
        "TestType": "Contrast"
    },
    {
        "Username": null,
        "TrialNumber": 7,
        "EyeCondition": "Right",
        "CorrectOption": "O",
        "GuessedOption": "O",
        "LogMAR": 0.0,
        "Eccentricity_d": 0.0,
        "Theta_d": 0.0,
        "LetterSize_m": 0.0,
        "LogDVA": 0.0,
        "DVA": 0.0,
        "ContrastAlpha_rgb": 160.65,
        "Alpha1": 161.0,
        "Alpha2": 160.0,
        "Ratio": 0.65,
        "LogLum": 0.20065945054641829,
        "IPD": 0,
        "TimeTakenToGuess_s": 2.68657,
        "Timestamp": "2024-11-23T15:34:28.700368+04:00",
        "TestType": "Contrast"
    },
    {
        "Username": null,
        "TrialNumber": 8,
        "EyeCondition": "Right",
        "CorrectOption": "D",
        "GuessedOption": "D",
        "LogMAR": 0.0,
        "Eccentricity_d": 0.0,
        "Theta_d": 0.0,
        "LetterSize_m": 0.0,
        "LogDVA": 0.0,
        "DVA": 0.0,
        "ContrastAlpha_rgb": 101.2095,
        "Alpha1": 102.0,
        "Alpha2": 101.0,
        "Ratio": 0.21,
        "LogLum": 0.40131890109283658,
        "IPD": 0,
        "TimeTakenToGuess_s": 2.853931,
        "Timestamp": "2024-11-23T15:34:33.280736+04:00",
        "TestType": "Contrast"
    },
    {
        "Username": null,
        "TrialNumber": 9,
        "EyeCondition": "Right",
        "CorrectOption": "C",
        "GuessedOption": "C",
        "LogMAR": 0.0,
        "Eccentricity_d": 0.0,
        "Theta_d": 0.0,
        "LetterSize_m": 0.0,
        "LogDVA": 0.0,
        "DVA": 0.0,
        "ContrastAlpha_rgb": 63.7619858,
        "Alpha1": 64.0,
        "Alpha2": 63.0,
        "Ratio": 0.76,
        "LogLum": 0.60197835163925484,
        "IPD": 0,
        "TimeTakenToGuess_s": 3.480921,
        "Timestamp": "2024-11-23T15:34:38.08413+04:00",
        "TestType": "Contrast"
    },
    {
        "Username": null,
        "TrialNumber": 10,
        "EyeCondition": "Right",
        "CorrectOption": "Z",
        "GuessedOption": "Z",
        "LogMAR": 0.0,
        "Eccentricity_d": 0.0,
        "Theta_d": 0.0,
        "LetterSize_m": 0.0,
        "LogDVA": 0.0,
        "DVA": 0.0,
        "ContrastAlpha_rgb": 40.17005,
        "Alpha1": 41.0,
        "Alpha2": 40.0,
        "Ratio": 0.17,
        "LogLum": 0.80263780218567315,
        "IPD": 0,
        "TimeTakenToGuess_s": 3.341133,
        "Timestamp": "2024-11-23T15:34:43.764364+04:00",
        "TestType": "Contrast"
    },
    {
        "Username": null,
        "TrialNumber": 11,
        "EyeCondition": "Right",
        "CorrectOption": "S",
        "GuessedOption": "S",
        "LogMAR": 0.0,
        "Eccentricity_d": 0.0,
        "Theta_d": 0.0,
        "LetterSize_m": 0.0,
        "LogDVA": 0.0,
        "DVA": 0.0,
        "ContrastAlpha_rgb": 25.3071327,
        "Alpha1": 26.0,
        "Alpha2": 25.0,
        "Ratio": 0.31,
        "LogLum": 1.0032972527320914,
        "IPD": 0,
        "TimeTakenToGuess_s": 2.854191,
        "Timestamp": "2024-11-23T15:34:48.999091+04:00",
        "TestType": "Contrast"
    },
    {
        "Username": null,
        "TrialNumber": 12,
        "EyeCondition": "Left",
        "CorrectOption": "K",
        "GuessedOption": "K",
        "LogMAR": 0.0,
        "Eccentricity_d": 0.0,
        "Theta_d": 0.0,
        "LetterSize_m": 0.0,
        "LogDVA": 0.0,
        "DVA": 0.0,
        "ContrastAlpha_rgb": 63.7619858,
        "Alpha1": 64.0,
        "Alpha2": 63.0,
        "Ratio": 0.76,
        "LogLum": 0.60197835163925484,
        "IPD": 0,
        "TimeTakenToGuess_s": 2.882065,
        "Timestamp": "2024-11-23T15:34:53.482092+04:00",
        "TestType": "Contrast"
    },
    {
        "Username": null,
        "TrialNumber": 13,
        "EyeCondition": "Both",
        "CorrectOption": "S",
        "GuessedOption": "S",
        "LogMAR": 0.0,
        "Eccentricity_d": 0.0,
        "Theta_d": 0.0,
        "LetterSize_m": 0.0,
        "LogDVA": 0.0,
        "DVA": 0.0,
        "ContrastAlpha_rgb": 101.2095,
        "Alpha1": 102.0,
        "Alpha2": 101.0,
        "Ratio": 0.21,
        "LogLum": 0.40131890109283658,
        "IPD": 0,
        "TimeTakenToGuess_s": 3.341445,
        "Timestamp": "2024-11-23T15:34:58.995182+04:00",
        "TestType": "Contrast"
    },
    {
        "Username": null,
        "TrialNumber": 14,
        "EyeCondition": "Left",
        "CorrectOption": "V",
        "GuessedOption": "V",
        "LogMAR": 0.0,
        "Eccentricity_d": 0.0,
        "Theta_d": 0.0,
        "LetterSize_m": 0.0,
        "LogDVA": 0.0,
        "DVA": 0.0,
        "ContrastAlpha_rgb": 40.17005,
        "Alpha1": 41.0,
        "Alpha2": 40.0,
        "Ratio": 0.17,
        "LogLum": 0.80263780218567315,
        "IPD": 0,
        "TimeTakenToGuess_s": 2.938024,
        "Timestamp": "2024-11-23T15:35:04.383061+04:00",
        "TestType": "Contrast"
    },
    {
        "Username": null,
        "TrialNumber": 15,
        "EyeCondition": "Right",
        "CorrectOption": "O",
        "GuessedOption": "O",
        "LogMAR": 0.0,
        "Eccentricity_d": 0.0,
        "Theta_d": 0.0,
        "LetterSize_m": 0.0,
        "LogDVA": 0.0,
        "DVA": 0.0,
        "ContrastAlpha_rgb": 15.9434929,
        "Alpha1": 16.0,
        "Alpha2": 15.0,
        "Ratio": 0.94,
        "LogLum": 1.2039567032785097,
        "IPD": 0,
        "TimeTakenToGuess_s": 2.784117,
        "Timestamp": "2024-11-23T15:35:09.214369+04:00",
        "TestType": "Contrast"
    },
    {
        "Username": null,
        "TrialNumber": 16,
        "EyeCondition": "Left",
        "CorrectOption": "R",
        "GuessedOption": "R",
        "LogMAR": 0.0,
        "Eccentricity_d": 0.0,
        "Theta_d": 0.0,
        "LetterSize_m": 0.0,
        "LogDVA": 0.0,
        "DVA": 0.0,
        "ContrastAlpha_rgb": 25.3071327,
        "Alpha1": 26.0,
        "Alpha2": 25.0,
        "Ratio": 0.31,
        "LogLum": 1.0032972527320914,
        "IPD": 0,
        "TimeTakenToGuess_s": 2.798513,
        "Timestamp": "2024-11-23T15:35:14.838902+04:00",
        "TestType": "Contrast"
    },
    {
        "Username": null,
        "TrialNumber": 17,
        "EyeCondition": "Both",
        "CorrectOption": "D",
        "GuessedOption": "D",
        "LogMAR": 0.0,
        "Eccentricity_d": 0.0,
        "Theta_d": 0.0,
        "LetterSize_m": 0.0,
        "LogDVA": 0.0,
        "DVA": 0.0,
        "ContrastAlpha_rgb": 63.7619858,
        "Alpha1": 64.0,
        "Alpha2": 63.0,
        "Ratio": 0.76,
        "LogLum": 0.60197835163925484,
        "IPD": 0,
        "TimeTakenToGuess_s": 2.85379,
        "Timestamp": "2024-11-23T15:35:19.614195+04:00",
        "TestType": "Contrast"
    },
    {
        "Username": null,
        "TrialNumber": 18,
        "EyeCondition": "Left",
        "CorrectOption": "C",
        "GuessedOption": "C",
        "LogMAR": 0.0,
        "Eccentricity_d": 0.0,
        "Theta_d": 0.0,
        "LetterSize_m": 0.0,
        "LogDVA": 0.0,
        "DVA": 0.0,
        "ContrastAlpha_rgb": 15.9434929,
        "Alpha1": 16.0,
        "Alpha2": 15.0,
        "Ratio": 0.94,
        "LogLum": 1.2039567032785097,
        "IPD": 0,
        "TimeTakenToGuess_s": 2.798245,
        "Timestamp": "2024-11-23T15:35:24.361727+04:00",
        "TestType": "Contrast"
    },
    {
        "Username": null,
        "TrialNumber": 19,
        "EyeCondition": "Right",
        "CorrectOption": "N",
        "GuessedOption": "D",
        "LogMAR": 0.0,
        "Eccentricity_d": 0.0,
        "Theta_d": 0.0,
        "LetterSize_m": 0.0,
        "LogDVA": 0.0,
        "DVA": 0.0,
        "ContrastAlpha_rgb": 10.0444,
        "Alpha1": 11.0,
        "Alpha2": 10.0,
        "Ratio": 0.04,
        "LogLum": 1.404616153824928,
        "IPD": 0,
        "TimeTakenToGuess_s": 3.396864,
        "Timestamp": "2024-11-23T15:35:29.03958+04:00",
        "TestType": "Contrast"
    },
    {
        "Username": null,
        "TrialNumber": 20,
        "EyeCondition": "Right",
        "CorrectOption": "K",
        "GuessedOption": "H",
        "LogMAR": 0.0,
        "Eccentricity_d": 0.0,
        "Theta_d": 0.0,
        "LetterSize_m": 0.0,
        "LogDVA": 0.0,
        "DVA": 0.0,
        "ContrastAlpha_rgb": 15.9434929,
        "Alpha1": 16.0,
        "Alpha2": 15.0,
        "Ratio": 0.94,
        "LogLum": 1.2039567032785097,
        "IPD": 0,
        "TimeTakenToGuess_s": 4.858351,
        "Timestamp": "2024-11-23T15:35:34.330145+04:00",
        "TestType": "Contrast"
    },
    {
        "Username": null,
        "TrialNumber": 21,
        "EyeCondition": "Both",
        "CorrectOption": "C",
        "GuessedOption": "C",
        "LogMAR": 0.0,
        "Eccentricity_d": 0.0,
        "Theta_d": 0.0,
        "LetterSize_m": 0.0,
        "LogDVA": 0.0,
        "DVA": 0.0,
        "ContrastAlpha_rgb": 40.17005,
        "Alpha1": 41.0,
        "Alpha2": 40.0,
        "Ratio": 0.17,
        "LogLum": 0.80263780218567315,
        "IPD": 0,
        "TimeTakenToGuess_s": 2.714707,
        "Timestamp": "2024-11-23T15:35:41.541913+04:00",
        "TestType": "Contrast"
    },
    {
        "Username": null,
        "TrialNumber": 22,
        "EyeCondition": "Right",
        "CorrectOption": "H",
        "GuessedOption": "H",
        "LogMAR": 0.0,
        "Eccentricity_d": 0.0,
        "Theta_d": 0.0,
        "LetterSize_m": 0.0,
        "LogDVA": 0.0,
        "DVA": 0.0,
        "ContrastAlpha_rgb": 20.0869141,
        "Alpha1": 21.0,
        "Alpha2": 20.0,
        "Ratio": 0.09,
        "LogLum": 1.1036269780053005,
        "IPD": 0,
        "TimeTakenToGuess_s": 2.631119,
        "Timestamp": "2024-11-23T15:35:46.317187+04:00",
        "TestType": "Contrast"
    },
    {
        "Username": null,
        "TrialNumber": 23,
        "EyeCondition": "Left",
        "CorrectOption": "C",
        "GuessedOption": "S",
        "LogMAR": 0.0,
        "Eccentricity_d": 0.0,
        "Theta_d": 0.0,
        "LetterSize_m": 0.0,
        "LogDVA": 0.0,
        "DVA": 0.0,
        "ContrastAlpha_rgb": 10.0444,
        "Alpha1": 11.0,
        "Alpha2": 10.0,
        "Ratio": 0.04,
        "LogLum": 1.404616153824928,
        "IPD": 0,
        "TimeTakenToGuess_s": 2.700653,
        "Timestamp": "2024-11-23T15:35:50.744509+04:00",
        "TestType": "Contrast"
    },
    {
        "Username": null,
        "TrialNumber": 24,
        "EyeCondition": "Both",
        "CorrectOption": "R",
        "GuessedOption": "R",
        "LogMAR": 0.0,
        "Eccentricity_d": 0.0,
        "Theta_d": 0.0,
        "LetterSize_m": 0.0,
        "LogDVA": 0.0,
        "DVA": 0.0,
        "ContrastAlpha_rgb": 25.3071327,
        "Alpha1": 26.0,
        "Alpha2": 25.0,
        "Ratio": 0.31,
        "LogLum": 1.0032972527320914,
        "IPD": 0,
        "TimeTakenToGuess_s": 2.5337,
        "Timestamp": "2024-11-23T15:35:55.185574+04:00",
        "TestType": "Contrast"
    },
    {
        "Username": null,
        "TrialNumber": 25,
        "EyeCondition": "Both",
        "CorrectOption": "R",
        "GuessedOption": "R",
        "LogMAR": 0.0,
        "Eccentricity_d": 0.0,
        "Theta_d": 0.0,
        "LetterSize_m": 0.0,
        "LogDVA": 0.0,
        "DVA": 0.0,
        "ContrastAlpha_rgb": 15.9434929,
        "Alpha1": 16.0,
        "Alpha2": 15.0,
        "Ratio": 0.94,
        "LogLum": 1.2039567032785097,
        "IPD": 0,
        "TimeTakenToGuess_s": 2.700295,
        "Timestamp": "2024-11-23T15:35:59.849643+04:00",
        "TestType": "Contrast"
    },
    {
        "Username": null,
        "TrialNumber": 26,
        "EyeCondition": "Both",
        "CorrectOption": "V",
        "GuessedOption": "S",
        "LogMAR": 0.0,
        "Eccentricity_d": 0.0,
        "Theta_d": 0.0,
        "LetterSize_m": 0.0,
        "LogDVA": 0.0,
        "DVA": 0.0,
        "ContrastAlpha_rgb": 10.0444,
        "Alpha1": 11.0,
        "Alpha2": 10.0,
        "Ratio": 0.04,
        "LogLum": 1.404616153824928,
        "IPD": 0,
        "TimeTakenToGuess_s": 3.29947,
        "Timestamp": "2024-11-23T15:36:04.513408+04:00",
        "TestType": "Contrast"
    },
    {
        "Username": null,
        "TrialNumber": 27,
        "EyeCondition": "Left",
        "CorrectOption": "O",
        "GuessedOption": "C",
        "LogMAR": 0.0,
        "Eccentricity_d": 0.0,
        "Theta_d": 0.0,
        "LetterSize_m": 0.0,
        "LogDVA": 0.0,
        "DVA": 0.0,
        "ContrastAlpha_rgb": 15.9434929,
        "Alpha1": 16.0,
        "Alpha2": 15.0,
        "Ratio": 0.94,
        "LogLum": 1.2039567032785097,
        "IPD": 0,
        "TimeTakenToGuess_s": 2.964665,
        "Timestamp": "2024-11-23T15:36:09.762398+04:00",
        "TestType": "Contrast"
    },
    {
        "Username": null,
        "TrialNumber": 28,
        "EyeCondition": "Right",
        "CorrectOption": "C",
        "GuessedOption": "S",
        "LogMAR": 0.0,
        "Eccentricity_d": 0.0,
        "Theta_d": 0.0,
        "LetterSize_m": 0.0,
        "LogDVA": 0.0,
        "DVA": 0.0,
        "ContrastAlpha_rgb": 15.9434929,
        "Alpha1": 16.0,
        "Alpha2": 15.0,
        "Ratio": 0.94,
        "LogLum": 1.2039567032785097,
        "IPD": 0,
        "TimeTakenToGuess_s": 4.663694,
        "Timestamp": "2024-11-23T15:36:14.635145+04:00",
        "TestType": "Contrast"
    },
    {
        "Username": null,
        "TrialNumber": 29,
        "EyeCondition": "Left",
        "CorrectOption": "S",
        "GuessedOption": "S",
        "LogMAR": 0.0,
        "Eccentricity_d": 0.0,
        "Theta_d": 0.0,
        "LetterSize_m": 0.0,
        "LogDVA": 0.0,
        "DVA": 0.0,
        "ContrastAlpha_rgb": 20.0869141,
        "Alpha1": 21.0,
        "Alpha2": 20.0,
        "Ratio": 0.09,
        "LogLum": 1.1036269780053005,
        "IPD": 0,
        "TimeTakenToGuess_s": 3.006877,
        "Timestamp": "2024-11-23T15:36:21.415435+04:00",
        "TestType": "Contrast"
    },
    {
        "Username": null,
        "TrialNumber": 30,
        "EyeCondition": "Right",
        "CorrectOption": "N",
        "GuessedOption": "N",
        "LogMAR": 0.0,
        "Eccentricity_d": 0.0,
        "Theta_d": 0.0,
        "LetterSize_m": 0.0,
        "LogDVA": 0.0,
        "DVA": 0.0,
        "ContrastAlpha_rgb": 20.0869141,
        "Alpha1": 21.0,
        "Alpha2": 20.0,
        "Ratio": 0.09,
        "LogLum": 1.1036269780053005,
        "IPD": 0,
        "TimeTakenToGuess_s": 3.034866,
        "Timestamp": "2024-11-23T15:36:26.371709+04:00",
        "TestType": "Contrast"
    },
    {
        "Username": null,
        "TrialNumber": 31,
        "EyeCondition": "Both",
        "CorrectOption": "S",
        "GuessedOption": "S",
        "LogMAR": 0.0,
        "Eccentricity_d": 0.0,
        "Theta_d": 0.0,
        "LetterSize_m": 0.0,
        "LogDVA": 0.0,
        "DVA": 0.0,
        "ContrastAlpha_rgb": 15.9434929,
        "Alpha1": 16.0,
        "Alpha2": 15.0,
        "Ratio": 0.94,
        "LogLum": 1.2039567032785097,
        "IPD": 0,
        "TimeTakenToGuess_s": 2.853882,
        "Timestamp": "2024-11-23T15:36:31.662264+04:00",
        "TestType": "Contrast"
    },
    {
        "Username": null,
        "TrialNumber": 32,
        "EyeCondition": "Left",
        "CorrectOption": "H",
        "GuessedOption": "H",
        "LogMAR": 0.0,
        "Eccentricity_d": 0.0,
        "Theta_d": 0.0,
        "LetterSize_m": 0.0,
        "LogDVA": 0.0,
        "DVA": 0.0,
        "ContrastAlpha_rgb": 15.9434929,
        "Alpha1": 16.0,
        "Alpha2": 15.0,
        "Ratio": 0.94,
        "LogLum": 1.2039567032785097,
        "IPD": 0,
        "TimeTakenToGuess_s": 2.770419,
        "Timestamp": "2024-11-23T15:36:36.729951+04:00",
        "TestType": "Contrast"
    },
    {
        "Username": null,
        "TrialNumber": 33,
        "EyeCondition": "Both",
        "CorrectOption": "O",
        "GuessedOption": "O",
        "LogMAR": 0.0,
        "Eccentricity_d": 0.0,
        "Theta_d": 0.0,
        "LetterSize_m": 0.0,
        "LogDVA": 0.0,
        "DVA": 0.0,
        "ContrastAlpha_rgb": 12.6547556,
        "Alpha1": 13.0,
        "Alpha2": 12.0,
        "Ratio": 0.65,
        "LogLum": 1.3042864285517188,
        "IPD": 0,
        "TimeTakenToGuess_s": 2.978883,
        "Timestamp": "2024-11-23T15:36:41.79766+04:00",
        "TestType": "Contrast"
    },
    {
        "Username": null,
        "TrialNumber": 34,
        "EyeCondition": "Left",
        "CorrectOption": "C",
        "GuessedOption": "C",
        "LogMAR": 0.0,
        "Eccentricity_d": 0.0,
        "Theta_d": 0.0,
        "LetterSize_m": 0.0,
        "LogDVA": 0.0,
        "DVA": 0.0,
        "ContrastAlpha_rgb": 12.6547556,
        "Alpha1": 13.0,
        "Alpha2": 12.0,
        "Ratio": 0.65,
        "LogLum": 1.3042864285517188,
        "IPD": 0,
        "TimeTakenToGuess_s": 2.881722,
        "Timestamp": "2024-11-23T15:36:47.408315+04:00",
        "TestType": "Contrast"
    },
    {
        "Username": null,
        "TrialNumber": 35,
        "EyeCondition": "Both",
        "CorrectOption": "V",
        "GuessedOption": "H",
        "LogMAR": 0.0,
        "Eccentricity_d": 0.0,
        "Theta_d": 0.0,
        "LetterSize_m": 0.0,
        "LogDVA": 0.0,
        "DVA": 0.0,
        "ContrastAlpha_rgb": 10.0444,
        "Alpha1": 11.0,
        "Alpha2": 10.0,
        "Ratio": 0.04,
        "LogLum": 1.404616153824928,
        "IPD": 0,
        "TimeTakenToGuess_s": 3.368931,
        "Timestamp": "2024-11-23T15:36:52.309001+04:00",
        "TestType": "Contrast"
    },
    {
        "Username": null,
        "TrialNumber": 36,
        "EyeCondition": "Both",
        "CorrectOption": "Z",
        "GuessedOption": "Z",
        "LogMAR": 0.0,
        "Eccentricity_d": 0.0,
        "Theta_d": 0.0,
        "LetterSize_m": 0.0,
        "LogDVA": 0.0,
        "DVA": 0.0,
        "ContrastAlpha_rgb": 12.6547556,
        "Alpha1": 13.0,
        "Alpha2": 12.0,
        "Ratio": 0.65,
        "LogLum": 1.3042864285517188,
        "IPD": 0,
        "TimeTakenToGuess_s": 2.7704,
        "Timestamp": "2024-11-23T15:36:58.114533+04:00",
        "TestType": "Contrast"
    },
    {
        "Username": null,
        "TrialNumber": 37,
        "EyeCondition": "Right",
        "CorrectOption": "C",
        "GuessedOption": "C",
        "LogMAR": 0.0,
        "Eccentricity_d": 0.0,
        "Theta_d": 0.0,
        "LetterSize_m": 0.0,
        "LogDVA": 0.0,
        "DVA": 0.0,
        "ContrastAlpha_rgb": 17.8956852,
        "Alpha1": 18.0,
        "Alpha2": 17.0,
        "Ratio": 0.9,
        "LogLum": 1.153791840641905,
        "IPD": 0,
        "TimeTakenToGuess_s": 4.120592,
        "Timestamp": "2024-11-23T15:37:02.541915+04:00",
        "TestType": "Contrast"
    },
    {
        "Username": null,
        "TrialNumber": 38,
        "EyeCondition": "Right",
        "CorrectOption": "K",
        "GuessedOption": "N",
        "LogMAR": 0.0,
        "Eccentricity_d": 0.0,
        "Theta_d": 0.0,
        "LetterSize_m": 0.0,
        "LogDVA": 0.0,
        "DVA": 0.0,
        "ContrastAlpha_rgb": 15.9434929,
        "Alpha1": 16.0,
        "Alpha2": 15.0,
        "Ratio": 0.94,
        "LogLum": 1.2039567032785095,
        "IPD": 0,
        "TimeTakenToGuess_s": 3.034435,
        "Timestamp": "2024-11-23T15:37:09.113289+04:00",
        "TestType": "Contrast"
    },
    {
        "Username": null,
        "TrialNumber": 39,
        "EyeCondition": "Left",
        "CorrectOption": "S",
        "GuessedOption": "Z",
        "LogMAR": 0.0,
        "Eccentricity_d": 0.0,
        "Theta_d": 0.0,
        "LetterSize_m": 0.0,
        "LogDVA": 0.0,
        "DVA": 0.0,
        "ContrastAlpha_rgb": 10.0444,
        "Alpha1": 11.0,
        "Alpha2": 10.0,
        "Ratio": 0.04,
        "LogLum": 1.404616153824928,
        "IPD": 0,
        "TimeTakenToGuess_s": 2.9653,
        "Timestamp": "2024-11-23T15:37:14.055495+04:00",
        "TestType": "Contrast"
    },
    {
        "Username": null,
        "TrialNumber": 40,
        "EyeCondition": "Left",
        "CorrectOption": "K",
        "GuessedOption": "C",
        "LogMAR": 0.0,
        "Eccentricity_d": 0.0,
        "Theta_d": 0.0,
        "LetterSize_m": 0.0,
        "LogDVA": 0.0,
        "DVA": 0.0,
        "ContrastAlpha_rgb": 12.6547556,
        "Alpha1": 13.0,
        "Alpha2": 12.0,
        "Ratio": 0.65,
        "LogLum": 1.3042864285517188,
        "IPD": 0,
        "TimeTakenToGuess_s": 3.675462,
        "Timestamp": "2024-11-23T15:37:18.997631+04:00",
        "TestType": "Contrast"
    },
    {
        "Username": null,
        "TrialNumber": 41,
        "EyeCondition": "Right",
        "CorrectOption": "V",
        "GuessedOption": "Z",
        "LogMAR": 0.0,
        "Eccentricity_d": 0.0,
        "Theta_d": 0.0,
        "LetterSize_m": 0.0,
        "LogDVA": 0.0,
        "DVA": 0.0,
        "ContrastAlpha_rgb": 17.8956852,
        "Alpha1": 18.0,
        "Alpha2": 17.0,
        "Ratio": 0.9,
        "LogLum": 1.153791840641905,
        "IPD": 0,
        "TimeTakenToGuess_s": 3.563712,
        "Timestamp": "2024-11-23T15:37:24.942982+04:00",
        "TestType": "Contrast"
    },
    {
        "Username": null,
        "TrialNumber": 42,
        "EyeCondition": "Right",
        "CorrectOption": "O",
        "GuessedOption": "N",
        "LogMAR": 0.0,
        "Eccentricity_d": 0.0,
        "Theta_d": 0.0,
        "LetterSize_m": 0.0,
        "LogDVA": 0.0,
        "DVA": 0.0,
        "ContrastAlpha_rgb": 20.0869141,
        "Alpha1": 21.0,
        "Alpha2": 20.0,
        "Ratio": 0.09,
        "LogLum": 1.1036269780053005,
        "IPD": 0,
        "TimeTakenToGuess_s": 3.090349,
        "Timestamp": "2024-11-23T15:37:30.748462+04:00",
        "TestType": "Contrast"
    },
    {
        "Username": null,
        "TrialNumber": 43,
        "EyeCondition": "Right",
        "CorrectOption": "N",
        "GuessedOption": "N",
        "LogMAR": 0.0,
        "Eccentricity_d": 0.0,
        "Theta_d": 0.0,
        "LetterSize_m": 0.0,
        "LogDVA": 0.0,
        "DVA": 0.0,
        "ContrastAlpha_rgb": 22.5464439,
        "Alpha1": 23.0,
        "Alpha2": 22.0,
        "Ratio": 0.55,
        "LogLum": 1.0534621153686961,
        "IPD": 0,
        "TimeTakenToGuess_s": 2.631468,
        "Timestamp": "2024-11-23T15:37:35.746369+04:00",
        "TestType": "Contrast"
    },
    {
        "Username": null,
        "TrialNumber": 44,
        "EyeCondition": "Both",
        "CorrectOption": "H",
        "GuessedOption": "N",
        "LogMAR": 0.0,
        "Eccentricity_d": 0.0,
        "Theta_d": 0.0,
        "LetterSize_m": 0.0,
        "LogDVA": 0.0,
        "DVA": 0.0,
        "ContrastAlpha_rgb": 11.2742815,
        "Alpha1": 12.0,
        "Alpha2": 11.0,
        "Ratio": 0.27,
        "LogLum": 1.3544512911883233,
        "IPD": 0,
        "TimeTakenToGuess_s": 2.589052,
        "Timestamp": "2024-11-23T15:37:40.967623+04:00",
        "TestType": "Contrast"
    },
    {
        "Username": null,
        "TrialNumber": 45,
        "EyeCondition": "Both",
        "CorrectOption": "H",
        "GuessedOption": "N",
        "LogMAR": 0.0,
        "Eccentricity_d": 0.0,
        "Theta_d": 0.0,
        "LetterSize_m": 0.0,
        "LogDVA": 0.0,
        "DVA": 0.0,
        "ContrastAlpha_rgb": 12.6547556,
        "Alpha1": 13.0,
        "Alpha2": 12.0,
        "Ratio": 0.65,
        "LogLum": 1.3042864285517188,
        "IPD": 0,
        "TimeTakenToGuess_s": 2.756491,
        "Timestamp": "2024-11-23T15:37:45.478066+04:00",
        "TestType": "Contrast"
    },
    {
        "Username": null,
        "TrialNumber": 46,
        "EyeCondition": "Right",
        "CorrectOption": "S",
        "GuessedOption": "S",
        "LogMAR": 0.0,
        "Eccentricity_d": 0.0,
        "Theta_d": 0.0,
        "LetterSize_m": 0.0,
        "LogDVA": 0.0,
        "DVA": 0.0,
        "ContrastAlpha_rgb": 20.0869141,
        "Alpha1": 21.0,
        "Alpha2": 20.0,
        "Ratio": 0.09,
        "LogLum": 1.1036269780053005,
        "IPD": 0,
        "TimeTakenToGuess_s": 3.702913,
        "Timestamp": "2024-11-23T15:37:50.198023+04:00",
        "TestType": "Contrast"
    },
    {
        "Username": null,
        "TrialNumber": 47,
        "EyeCondition": "Left",
        "CorrectOption": "Z",
        "GuessedOption": "Z",
        "LogMAR": 0.0,
        "Eccentricity_d": 0.0,
        "Theta_d": 0.0,
        "LetterSize_m": 0.0,
        "LogDVA": 0.0,
        "DVA": 0.0,
        "ContrastAlpha_rgb": 14.20426,
        "Alpha1": 15.0,
        "Alpha2": 14.0,
        "Ratio": 0.2,
        "LogLum": 1.2541215659151144,
        "IPD": 0,
        "TimeTakenToGuess_s": 3.090322,
        "Timestamp": "2024-11-23T15:37:56.170749+04:00",
        "TestType": "Contrast"
    },
    {
        "Username": null,
        "TrialNumber": 48,
        "EyeCondition": "Left",
        "CorrectOption": "O",
        "GuessedOption": "C",
        "LogMAR": 0.0,
        "Eccentricity_d": 0.0,
        "Theta_d": 0.0,
        "LetterSize_m": 0.0,
        "LogDVA": 0.0,
        "DVA": 0.0,
        "ContrastAlpha_rgb": 12.6547556,
        "Alpha1": 13.0,
        "Alpha2": 12.0,
        "Ratio": 0.65,
        "LogLum": 1.3042864285517188,
        "IPD": 0,
        "TimeTakenToGuess_s": 3.382805,
        "Timestamp": "2024-11-23T15:38:01.001802+04:00",
        "TestType": "Contrast"
    },
    {
        "Username": null,
        "TrialNumber": 49,
        "EyeCondition": "Left",
        "CorrectOption": "O",
        "GuessedOption": "O",
        "LogMAR": 0.0,
        "Eccentricity_d": 0.0,
        "Theta_d": 0.0,
        "LetterSize_m": 0.0,
        "LogDVA": 0.0,
        "DVA": 0.0,
        "ContrastAlpha_rgb": 14.20426,
        "Alpha1": 15.0,
        "Alpha2": 14.0,
        "Ratio": 0.2,
        "LogLum": 1.2541215659151144,
        "IPD": 0,
        "TimeTakenToGuess_s": 2.589431,
        "Timestamp": "2024-11-23T15:38:06.904753+04:00",
        "TestType": "Contrast"
    },
    {
        "Username": null,
        "TrialNumber": 50,
        "EyeCondition": "Right",
        "CorrectOption": "Z",
        "GuessedOption": "Z",
        "LogMAR": 0.0,
        "Eccentricity_d": 0.0,
        "Theta_d": 0.0,
        "LetterSize_m": 0.0,
        "LogDVA": 0.0,
        "DVA": 0.0,
        "ContrastAlpha_rgb": 17.8956852,
        "Alpha1": 18.0,
        "Alpha2": 17.0,
        "Ratio": 0.9,
        "LogLum": 1.153791840641905,
        "IPD": 0,
        "TimeTakenToGuess_s": 3.201977,
        "Timestamp": "2024-11-23T15:38:11.457256+04:00",
        "TestType": "Contrast"
    },
    {
        "Username": null,
        "TrialNumber": 51,
        "EyeCondition": "Both",
        "CorrectOption": "O",
        "GuessedOption": "C",
        "LogMAR": 0.0,
        "Eccentricity_d": 0.0,
        "Theta_d": 0.0,
        "LetterSize_m": 0.0,
        "LogDVA": 0.0,
        "DVA": 0.0,
        "ContrastAlpha_rgb": 14.20426,
        "Alpha1": 15.0,
        "Alpha2": 14.0,
        "Ratio": 0.2,
        "LogLum": 1.2541215659151144,
        "IPD": 0,
        "TimeTakenToGuess_s": 3.925712,
        "Timestamp": "2024-11-23T15:38:16.413594+04:00",
        "TestType": "Contrast"
    },
    {
        "Username": null,
        "TrialNumber": 52,
        "EyeCondition": "Left",
        "CorrectOption": "Z",
        "GuessedOption": "Z",
        "LogMAR": 0.0,
        "Eccentricity_d": 0.0,
        "Theta_d": 0.0,
        "LetterSize_m": 0.0,
        "LogDVA": 0.0,
        "DVA": 0.0,
        "ContrastAlpha_rgb": 12.6547556,
        "Alpha1": 13.0,
        "Alpha2": 12.0,
        "Ratio": 0.65,
        "LogLum": 1.3042864285517188,
        "IPD": 0,
        "TimeTakenToGuess_s": 3.480589,
        "Timestamp": "2024-11-23T15:38:22.525388+04:00",
        "TestType": "Contrast"
    },
    {
        "Username": null,
        "TrialNumber": 53,
        "EyeCondition": "Left",
        "CorrectOption": "V",
        "GuessedOption": "Z",
        "LogMAR": 0.0,
        "Eccentricity_d": 0.0,
        "Theta_d": 0.0,
        "LetterSize_m": 0.0,
        "LogDVA": 0.0,
        "DVA": 0.0,
        "ContrastAlpha_rgb": 11.2742815,
        "Alpha1": 12.0,
        "Alpha2": 11.0,
        "Ratio": 0.27,
        "LogLum": 1.3544512911883233,
        "IPD": 0,
        "TimeTakenToGuess_s": 3.118299,
        "Timestamp": "2024-11-23T15:38:27.941292+04:00",
        "TestType": "Contrast"
    },
    {
        "Username": null,
        "TrialNumber": 54,
        "EyeCondition": "Right",
        "CorrectOption": "K",
        "GuessedOption": "S",
        "LogMAR": 0.0,
        "Eccentricity_d": 0.0,
        "Theta_d": 0.0,
        "LetterSize_m": 0.0,
        "LogDVA": 0.0,
        "DVA": 0.0,
        "ContrastAlpha_rgb": 15.9434929,
        "Alpha1": 16.0,
        "Alpha2": 15.0,
        "Ratio": 0.94,
        "LogLum": 1.2039567032785095,
        "IPD": 0,
        "TimeTakenToGuess_s": 3.3131,
        "Timestamp": "2024-11-23T15:38:33.050874+04:00",
        "TestType": "Contrast"
    },
    {
        "Username": null,
        "TrialNumber": 55,
        "EyeCondition": "Right",
        "CorrectOption": "C",
        "GuessedOption": "Z",
        "LogMAR": 0.0,
        "Eccentricity_d": 0.0,
        "Theta_d": 0.0,
        "LetterSize_m": 0.0,
        "LogDVA": 0.0,
        "DVA": 0.0,
        "ContrastAlpha_rgb": 17.8956852,
        "Alpha1": 18.0,
        "Alpha2": 17.0,
        "Ratio": 0.9,
        "LogLum": 1.153791840641905,
        "IPD": 0,
        "TimeTakenToGuess_s": 3.967732,
        "Timestamp": "2024-11-23T15:38:38.494359+04:00",
        "TestType": "Contrast"
    },
    {
        "Username": null,
        "TrialNumber": 56,
        "EyeCondition": "Both",
        "CorrectOption": "V",
        "GuessedOption": "V",
        "LogMAR": 0.0,
        "Eccentricity_d": 0.0,
        "Theta_d": 0.0,
        "LetterSize_m": 0.0,
        "LogDVA": 0.0,
        "DVA": 0.0,
        "ContrastAlpha_rgb": 15.9434929,
        "Alpha1": 16.0,
        "Alpha2": 15.0,
        "Ratio": 0.94,
        "LogLum": 1.20395670327851,
        "IPD": 0,
        "TimeTakenToGuess_s": 3.13215,
        "Timestamp": "2024-11-23T15:38:44.258364+04:00",
        "TestType": "Contrast"
    },
    {
        "Username": null,
        "TrialNumber": 57,
        "EyeCondition": "Both",
        "CorrectOption": "K",
        "GuessedOption": "K",
        "LogMAR": 0.0,
        "Eccentricity_d": 0.0,
        "Theta_d": 0.0,
        "LetterSize_m": 0.0,
        "LogDVA": 0.0,
        "DVA": 0.0,
        "ContrastAlpha_rgb": 14.20426,
        "Alpha1": 15.0,
        "Alpha2": 14.0,
        "Ratio": 0.2,
        "LogLum": 1.2541215659151144,
        "IPD": 0,
        "TimeTakenToGuess_s": 2.965013,
        "Timestamp": "2024-11-23T15:38:51.344896+04:00",
        "TestType": "Contrast"
    },
    {
        "Username": null,
        "TrialNumber": 58,
        "EyeCondition": "Left",
        "CorrectOption": "H",
        "GuessedOption": "Z",
        "LogMAR": 0.0,
        "Eccentricity_d": 0.0,
        "Theta_d": 0.0,
        "LetterSize_m": 0.0,
        "LogDVA": 0.0,
        "DVA": 0.0,
        "ContrastAlpha_rgb": 12.6547556,
        "Alpha1": 13.0,
        "Alpha2": 12.0,
        "Ratio": 0.65,
        "LogLum": 1.3042864285517188,
        "IPD": 0,
        "TimeTakenToGuess_s": 3.480266,
        "Timestamp": "2024-11-23T15:38:55.785898+04:00",
        "TestType": "Contrast"
    },
    {
        "Username": null,
        "TrialNumber": 59,
        "EyeCondition": "Left",
        "CorrectOption": "H",
        "GuessedOption": "Z",
        "LogMAR": 0.0,
        "Eccentricity_d": 0.0,
        "Theta_d": 0.0,
        "LetterSize_m": 0.0,
        "LogDVA": 0.0,
        "DVA": 0.0,
        "ContrastAlpha_rgb": 13.4071407,
        "Alpha1": 14.0,
        "Alpha2": 13.0,
        "Ratio": 0.41,
        "LogLum": 1.2792039972334166,
        "IPD": 0,
        "TimeTakenToGuess_s": 2.67276,
        "Timestamp": "2024-11-23T15:39:01.118228+04:00",
        "TestType": "Contrast"
    },
    {
        "Username": null,
        "TrialNumber": 60,
        "EyeCondition": "Right",
        "CorrectOption": "S",
        "GuessedOption": "H",
        "LogMAR": 0.0,
        "Eccentricity_d": 0.0,
        "Theta_d": 0.0,
        "LetterSize_m": 0.0,
        "LogDVA": 0.0,
        "DVA": 0.0,
        "ContrastAlpha_rgb": 18.95967,
        "Alpha1": 19.0,
        "Alpha2": 18.0,
        "Ratio": 0.96,
        "LogLum": 1.1287094093236028,
        "IPD": 0,
        "TimeTakenToGuess_s": 3.048672,
        "Timestamp": "2024-11-23T15:39:05.503805+04:00",
        "TestType": "Contrast"
    },
    {
        "Username": null,
        "TrialNumber": 61,
        "EyeCondition": "Both",
        "CorrectOption": "O",
        "GuessedOption": "C",
        "LogMAR": 0.0,
        "Eccentricity_d": 0.0,
        "Theta_d": 0.0,
        "LetterSize_m": 0.0,
        "LogDVA": 0.0,
        "DVA": 0.0,
        "ContrastAlpha_rgb": 12.6547556,
        "Alpha1": 13.0,
        "Alpha2": 12.0,
        "Ratio": 0.65,
        "LogLum": 1.3042864285517188,
        "IPD": 0,
        "TimeTakenToGuess_s": 3.09033,
        "Timestamp": "2024-11-23T15:39:10.474212+04:00",
        "TestType": "Contrast"
    },
    {
        "Username": null,
        "TrialNumber": 62,
        "EyeCondition": "Both",
        "CorrectOption": "D",
        "GuessedOption": "D",
        "LogMAR": 0.0,
        "Eccentricity_d": 0.0,
        "Theta_d": 0.0,
        "LetterSize_m": 0.0,
        "LogDVA": 0.0,
        "DVA": 0.0,
        "ContrastAlpha_rgb": 14.20426,
        "Alpha1": 15.0,
        "Alpha2": 14.0,
        "Ratio": 0.2,
        "LogLum": 1.2541215659151144,
        "IPD": 0,
        "TimeTakenToGuess_s": 2.686644,
        "Timestamp": "2024-11-23T15:39:16.460682+04:00",
        "TestType": "Contrast"
    },
    {
        "Username": null,
        "TrialNumber": 63,
        "EyeCondition": "Left",
        "CorrectOption": "D",
        "GuessedOption": "R",
        "LogMAR": 0.0,
        "Eccentricity_d": 0.0,
        "Theta_d": 0.0,
        "LetterSize_m": 0.0,
        "LogDVA": 0.0,
        "DVA": 0.0,
        "ContrastAlpha_rgb": 14.20426,
        "Alpha1": 15.0,
        "Alpha2": 14.0,
        "Ratio": 0.2,
        "LogLum": 1.2541215659151144,
        "IPD": 0,
        "TimeTakenToGuess_s": 3.911807,
        "Timestamp": "2024-11-23T15:39:21.152374+04:00",
        "TestType": "Contrast"
    },
    {
        "Username": null,
        "TrialNumber": 64,
        "EyeCondition": "Right",
        "CorrectOption": "D",
        "GuessedOption": "D",
        "LogMAR": 0.0,
        "Eccentricity_d": 0.0,
        "Theta_d": 0.0,
        "LetterSize_m": 0.0,
        "LogDVA": 0.0,
        "DVA": 0.0,
        "ContrastAlpha_rgb": 20.0869141,
        "Alpha1": 21.0,
        "Alpha2": 20.0,
        "Ratio": 0.09,
        "LogLum": 1.1036269780053005,
        "IPD": 0,
        "TimeTakenToGuess_s": 2.839826,
        "Timestamp": "2024-11-23T15:39:27.319894+04:00",
        "TestType": "Contrast"
    },
    {
        "Username": null,
        "TrialNumber": 65,
        "EyeCondition": "Right",
        "CorrectOption": "Z",
        "GuessedOption": "Z",
        "LogMAR": 0.0,
        "Eccentricity_d": 0.0,
        "Theta_d": 0.0,
        "LetterSize_m": 0.0,
        "LogDVA": 0.0,
        "DVA": 0.0,
        "ContrastAlpha_rgb": 18.95967,
        "Alpha1": 19.0,
        "Alpha2": 18.0,
        "Ratio": 0.96,
        "LogLum": 1.1287094093236028,
        "IPD": 0,
        "TimeTakenToGuess_s": 3.076428,
        "Timestamp": "2024-11-23T15:39:32.248586+04:00",
        "TestType": "Contrast"
    },
    {
        "Username": null,
        "TrialNumber": 66,
        "EyeCondition": "Left",
        "CorrectOption": "R",
        "GuessedOption": "R",
        "LogMAR": 0.0,
        "Eccentricity_d": 0.0,
        "Theta_d": 0.0,
        "LetterSize_m": 0.0,
        "LogDVA": 0.0,
        "DVA": 0.0,
        "ContrastAlpha_rgb": 15.0487719,
        "Alpha1": 16.0,
        "Alpha2": 15.0,
        "Ratio": 0.05,
        "LogLum": 1.2290391345968121,
        "IPD": 0,
        "TimeTakenToGuess_s": 2.811865,
        "Timestamp": "2024-11-23T15:39:37.121442+04:00",
        "TestType": "Contrast"
    },
    {
        "Username": null,
        "TrialNumber": 67,
        "EyeCondition": "Both",
        "CorrectOption": "R",
        "GuessedOption": "R",
        "LogMAR": 0.0,
        "Eccentricity_d": 0.0,
        "Theta_d": 0.0,
        "LetterSize_m": 0.0,
        "LogDVA": 0.0,
        "DVA": 0.0,
        "ContrastAlpha_rgb": 13.4071407,
        "Alpha1": 14.0,
        "Alpha2": 13.0,
        "Ratio": 0.41,
        "LogLum": 1.2792039972334166,
        "IPD": 0,
        "TimeTakenToGuess_s": 2.853954,
        "Timestamp": "2024-11-23T15:39:41.799144+04:00",
        "TestType": "Contrast"
    },
    {
        "Username": null,
        "TrialNumber": 68,
        "EyeCondition": "Right",
        "CorrectOption": "N",
        "GuessedOption": "K",
        "LogMAR": 0.0,
        "Eccentricity_d": 0.0,
        "Theta_d": 0.0,
        "LetterSize_m": 0.0,
        "LogDVA": 0.0,
        "DVA": 0.0,
        "ContrastAlpha_rgb": 17.8956852,
        "Alpha1": 18.0,
        "Alpha2": 17.0,
        "Ratio": 0.9,
        "LogLum": 1.153791840641905,
        "IPD": 0,
        "TimeTakenToGuess_s": 3.285598,
        "Timestamp": "2024-11-23T15:39:46.490892+04:00",
        "TestType": "Contrast"
    },
    {
        "Username": null,
        "TrialNumber": 69,
        "EyeCondition": "Left",
        "CorrectOption": "S",
        "GuessedOption": "S",
        "LogMAR": 0.0,
        "Eccentricity_d": 0.0,
        "Theta_d": 0.0,
        "LetterSize_m": 0.0,
        "LogDVA": 0.0,
        "DVA": 0.0,
        "ContrastAlpha_rgb": 14.20426,
        "Alpha1": 15.0,
        "Alpha2": 14.0,
        "Ratio": 0.2,
        "LogLum": 1.2541215659151144,
        "IPD": 0,
        "TimeTakenToGuess_s": 3.689015,
        "Timestamp": "2024-11-23T15:39:52.059998+04:00",
        "TestType": "Contrast"
    },
    {
        "Username": null,
        "TrialNumber": 70,
        "EyeCondition": "Both",
        "CorrectOption": "V",
        "GuessedOption": "V",
        "LogMAR": 0.0,
        "Eccentricity_d": 0.0,
        "Theta_d": 0.0,
        "LetterSize_m": 0.0,
        "LogDVA": 0.0,
        "DVA": 0.0,
        "ContrastAlpha_rgb": 12.6547556,
        "Alpha1": 13.0,
        "Alpha2": 12.0,
        "Ratio": 0.65,
        "LogLum": 1.3042864285517188,
        "IPD": 0,
        "TimeTakenToGuess_s": 3.202,
        "Timestamp": "2024-11-23T15:39:57.865446+04:00",
        "TestType": "Contrast"
    },
    {
        "Username": null,
        "TrialNumber": 71,
        "EyeCondition": "Left",
        "CorrectOption": "N",
        "GuessedOption": "K",
        "LogMAR": 0.0,
        "Eccentricity_d": 0.0,
        "Theta_d": 0.0,
        "LetterSize_m": 0.0,
        "LogDVA": 0.0,
        "DVA": 0.0,
        "ContrastAlpha_rgb": 13.4071407,
        "Alpha1": 14.0,
        "Alpha2": 13.0,
        "Ratio": 0.41,
        "LogLum": 1.2792039972334166,
        "IPD": 0,
        "TimeTakenToGuess_s": 3.59176,
        "Timestamp": "2024-11-23T15:40:03.197805+04:00",
        "TestType": "Contrast"
    },
    {
        "Username": null,
        "TrialNumber": 72,
        "EyeCondition": "Left",
        "CorrectOption": "C",
        "GuessedOption": "C",
        "LogMAR": 0.0,
        "Eccentricity_d": 0.0,
        "Theta_d": 0.0,
        "LetterSize_m": 0.0,
        "LogDVA": 0.0,
        "DVA": 0.0,
        "ContrastAlpha_rgb": 14.20426,
        "Alpha1": 15.0,
        "Alpha2": 14.0,
        "Ratio": 0.2,
        "LogLum": 1.2541215659151144,
        "IPD": 0,
        "TimeTakenToGuess_s": 3.062882,
        "Timestamp": "2024-11-23T15:40:09.142381+04:00",
        "TestType": "Contrast"
    },
    {
        "Username": null,
        "TrialNumber": 73,
        "EyeCondition": "Both",
        "CorrectOption": "C",
        "GuessedOption": "K",
        "LogMAR": 0.0,
        "Eccentricity_d": 0.0,
        "Theta_d": 0.0,
        "LetterSize_m": 0.0,
        "LogDVA": 0.0,
        "DVA": 0.0,
        "ContrastAlpha_rgb": 11.9445925,
        "Alpha1": 12.0,
        "Alpha2": 11.0,
        "Ratio": 0.94,
        "LogLum": 1.3293688598700211,
        "IPD": 0,
        "TimeTakenToGuess_s": 3.981446,
        "Timestamp": "2024-11-23T15:40:14.683796+04:00",
        "TestType": "Contrast"
    },
    {
        "Username": null,
        "TrialNumber": 74,
        "EyeCondition": "Right",
        "CorrectOption": "Z",
        "GuessedOption": "Z",
        "LogMAR": 0.0,
        "Eccentricity_d": 0.0,
        "Theta_d": 0.0,
        "LetterSize_m": 0.0,
        "LogDVA": 0.0,
        "DVA": 0.0,
        "ContrastAlpha_rgb": 18.95967,
        "Alpha1": 19.0,
        "Alpha2": 18.0,
        "Ratio": 0.96,
        "LogLum": 1.1287094093236028,
        "IPD": 0,
        "TimeTakenToGuess_s": 2.603364,
        "Timestamp": "2024-11-23T15:40:20.767454+04:00",
        "TestType": "Contrast"
    },
    {
        "Username": null,
        "TrialNumber": 75,
        "EyeCondition": "Right",
        "CorrectOption": "O",
        "GuessedOption": "C",
        "LogMAR": 0.0,
        "Eccentricity_d": 0.0,
        "Theta_d": 0.0,
        "LetterSize_m": 0.0,
        "LogDVA": 0.0,
        "DVA": 0.0,
        "ContrastAlpha_rgb": 17.8956852,
        "Alpha1": 18.0,
        "Alpha2": 17.0,
        "Ratio": 0.9,
        "LogLum": 1.153791840641905,
        "IPD": 0,
        "TimeTakenToGuess_s": 3.02082,
        "Timestamp": "2024-11-23T15:40:25.083689+04:00",
        "TestType": "Contrast"
    },
    {
        "Username": null,
        "TrialNumber": 76,
        "EyeCondition": "Right",
        "CorrectOption": "D",
        "GuessedOption": "D",
        "LogMAR": 0.0,
        "Eccentricity_d": 0.0,
        "Theta_d": 0.0,
        "LetterSize_m": 0.0,
        "LogDVA": 0.0,
        "DVA": 0.0,
        "ContrastAlpha_rgb": 18.95967,
        "Alpha1": 19.0,
        "Alpha2": 18.0,
        "Ratio": 0.96,
        "LogLum": 1.1287094093236028,
        "IPD": 0,
        "TimeTakenToGuess_s": 3.09395,
        "Timestamp": "2024-11-23T15:40:30.388111+04:00",
        "TestType": "Contrast"
    },
    {
        "Username": null,
        "TrialNumber": 77,
        "EyeCondition": "Left",
        "CorrectOption": "K",
        "GuessedOption": "K",
        "LogMAR": 0.0,
        "Eccentricity_d": 0.0,
        "Theta_d": 0.0,
        "LetterSize_m": 0.0,
        "LogDVA": 0.0,
        "DVA": 0.0,
        "ContrastAlpha_rgb": 13.4071407,
        "Alpha1": 14.0,
        "Alpha2": 13.0,
        "Ratio": 0.41,
        "LogLum": 1.2792039972334166,
        "IPD": 0,
        "TimeTakenToGuess_s": 2.812023,
        "Timestamp": "2024-11-23T15:40:35.525355+04:00",
        "TestType": "Contrast"
    },
    {
        "Username": null,
        "TrialNumber": 78,
        "EyeCondition": "Left",
        "CorrectOption": "N",
        "GuessedOption": "R",
        "LogMAR": 0.0,
        "Eccentricity_d": 0.0,
        "Theta_d": 0.0,
        "LetterSize_m": 0.0,
        "LogDVA": 0.0,
        "DVA": 0.0,
        "ContrastAlpha_rgb": 12.6547556,
        "Alpha1": 13.0,
        "Alpha2": 12.0,
        "Ratio": 0.65,
        "LogLum": 1.3042864285517188,
        "IPD": 0,
        "TimeTakenToGuess_s": 3.118506,
        "Timestamp": "2024-11-23T15:40:40.523458+04:00",
        "TestType": "Contrast"
    },
    {
        "Username": null,
        "TrialNumber": 79,
        "EyeCondition": "Right",
        "CorrectOption": "N",
        "GuessedOption": "N",
        "LogMAR": 0.0,
        "Eccentricity_d": 0.0,
        "Theta_d": 0.0,
        "LetterSize_m": 0.0,
        "LogDVA": 0.0,
        "DVA": 0.0,
        "ContrastAlpha_rgb": 17.8956852,
        "Alpha1": 18.0,
        "Alpha2": 17.0,
        "Ratio": 0.9,
        "LogLum": 1.153791840641905,
        "IPD": 0,
        "TimeTakenToGuess_s": 2.784114,
        "Timestamp": "2024-11-23T15:40:45.758333+04:00",
        "TestType": "Contrast"
    },
    {
        "Username": null,
        "TrialNumber": 80,
        "EyeCondition": "Right",
        "CorrectOption": "Z",
        "GuessedOption": "Z",
        "LogMAR": 0.0,
        "Eccentricity_d": 0.0,
        "Theta_d": 0.0,
        "LetterSize_m": 0.0,
        "LogDVA": 0.0,
        "DVA": 0.0,
        "ContrastAlpha_rgb": 16.89141,
        "Alpha1": 17.0,
        "Alpha2": 16.0,
        "Ratio": 0.89,
        "LogLum": 1.1788742719602072,
        "IPD": 0,
        "TimeTakenToGuess_s": 2.68682,
        "Timestamp": "2024-11-23T15:40:50.617227+04:00",
        "TestType": "Contrast"
    },
    {
        "Username": null,
        "TrialNumber": 81,
        "EyeCondition": "Both",
        "CorrectOption": "R",
        "GuessedOption": "R",
        "LogMAR": 0.0,
        "Eccentricity_d": 0.0,
        "Theta_d": 0.0,
        "LetterSize_m": 0.0,
        "LogDVA": 0.0,
        "DVA": 0.0,
        "ContrastAlpha_rgb": 12.6547556,
        "Alpha1": 13.0,
        "Alpha2": 12.0,
        "Ratio": 0.65,
        "LogLum": 1.3042864285517188,
        "IPD": 0,
        "TimeTakenToGuess_s": 3.911753,
        "Timestamp": "2024-11-23T15:40:55.615419+04:00",
        "TestType": "Contrast"
    },
    {
        "Username": null,
        "TrialNumber": 82,
        "EyeCondition": "Both",
        "CorrectOption": "S",
        "GuessedOption": "S",
        "LogMAR": 0.0,
        "Eccentricity_d": 0.0,
        "Theta_d": 0.0,
        "LetterSize_m": 0.0,
        "LogDVA": 0.0,
        "DVA": 0.0,
        "ContrastAlpha_rgb": 11.9445925,
        "Alpha1": 12.0,
        "Alpha2": 11.0,
        "Ratio": 0.94,
        "LogLum": 1.3293688598700211,
        "IPD": 0,
        "TimeTakenToGuess_s": 3.285516,
        "Timestamp": "2024-11-23T15:41:01.657492+04:00",
        "TestType": "Contrast"
    },
    {
        "Username": null,
        "TrialNumber": 83,
        "EyeCondition": "Right",
        "CorrectOption": "V",
        "GuessedOption": "V",
        "LogMAR": 0.0,
        "Eccentricity_d": 0.0,
        "Theta_d": 0.0,
        "LetterSize_m": 0.0,
        "LogDVA": 0.0,
        "DVA": 0.0,
        "ContrastAlpha_rgb": 15.9434929,
        "Alpha1": 16.0,
        "Alpha2": 15.0,
        "Ratio": 0.94,
        "LogLum": 1.2039567032785095,
        "IPD": 0,
        "TimeTakenToGuess_s": 4.107007,
        "Timestamp": "2024-11-23T15:41:06.669539+04:00",
        "TestType": "Contrast"
    },
    {
        "Username": null,
        "TrialNumber": 84,
        "EyeCondition": "Both",
        "CorrectOption": "R",
        "GuessedOption": "N",
        "LogMAR": 0.0,
        "Eccentricity_d": 0.0,
        "Theta_d": 0.0,
        "LetterSize_m": 0.0,
        "LogDVA": 0.0,
        "DVA": 0.0,
        "ContrastAlpha_rgb": 11.2742815,
        "Alpha1": 12.0,
        "Alpha2": 11.0,
        "Ratio": 0.27,
        "LogLum": 1.3544512911883233,
        "IPD": 0,
        "TimeTakenToGuess_s": 2.700499,
        "Timestamp": "2024-11-23T15:41:12.990429+04:00",
        "TestType": "Contrast"
    },
    {
        "Username": null,
        "TrialNumber": 85,
        "EyeCondition": "Right",
        "CorrectOption": "K",
        "GuessedOption": "K",
        "LogMAR": 0.0,
        "Eccentricity_d": 0.0,
        "Theta_d": 0.0,
        "LetterSize_m": 0.0,
        "LogDVA": 0.0,
        "DVA": 0.0,
        "ContrastAlpha_rgb": 15.0487719,
        "Alpha1": 16.0,
        "Alpha2": 15.0,
        "Ratio": 0.05,
        "LogLum": 1.2290391345968117,
        "IPD": 0,
        "TimeTakenToGuess_s": 2.923206,
        "Timestamp": "2024-11-23T15:41:17.765753+04:00",
        "TestType": "Contrast"
    },
    {
        "Username": null,
        "TrialNumber": 86,
        "EyeCondition": "Both",
        "CorrectOption": "N",
        "GuessedOption": "N",
        "LogMAR": 0.0,
        "Eccentricity_d": 0.0,
        "Theta_d": 0.0,
        "LetterSize_m": 0.0,
        "LogDVA": 0.0,
        "DVA": 0.0,
        "ContrastAlpha_rgb": 11.9445925,
        "Alpha1": 12.0,
        "Alpha2": 11.0,
        "Ratio": 0.94,
        "LogLum": 1.3293688598700211,
        "IPD": 0,
        "TimeTakenToGuess_s": 2.728824,
        "Timestamp": "2024-11-23T15:41:23.334411+04:00",
        "TestType": "Contrast"
    },
    {
        "Username": null,
        "TrialNumber": 87,
        "EyeCondition": "Both",
        "CorrectOption": "H",
        "GuessedOption": "H",
        "LogMAR": 0.0,
        "Eccentricity_d": 0.0,
        "Theta_d": 0.0,
        "LetterSize_m": 0.0,
        "LogDVA": 0.0,
        "DVA": 0.0,
        "ContrastAlpha_rgb": 11.2742815,
        "Alpha1": 12.0,
        "Alpha2": 11.0,
        "Ratio": 0.27,
        "LogLum": 1.3544512911883233,
        "IPD": 0,
        "TimeTakenToGuess_s": 4.106787,
        "Timestamp": "2024-11-23T15:41:28.318704+04:00",
        "TestType": "Contrast"
    },
    {
        "Username": null,
        "TrialNumber": 88,
        "EyeCondition": "Both",
        "CorrectOption": "R",
        "GuessedOption": "N",
        "LogMAR": 0.0,
        "Eccentricity_d": 0.0,
        "Theta_d": 0.0,
        "LetterSize_m": 0.0,
        "LogDVA": 0.0,
        "DVA": 0.0,
        "ContrastAlpha_rgb": 10.6415882,
        "Alpha1": 11.0,
        "Alpha2": 10.0,
        "Ratio": 0.64,
        "LogLum": 1.3795337225066255,
        "IPD": 0,
        "TimeTakenToGuess_s": 3.911908,
        "Timestamp": "2024-11-23T15:41:34.583817+04:00",
        "TestType": "Contrast"
    },
    {
        "Username": null,
        "TrialNumber": 89,
        "EyeCondition": "Both",
        "CorrectOption": "D",
        "GuessedOption": "N",
        "LogMAR": 0.0,
        "Eccentricity_d": 0.0,
        "Theta_d": 0.0,
        "LetterSize_m": 0.0,
        "LogDVA": 0.0,
        "DVA": 0.0,
        "ContrastAlpha_rgb": 11.2742815,
        "Alpha1": 12.0,
        "Alpha2": 11.0,
        "Ratio": 0.27,
        "LogLum": 1.3544512911883233,
        "IPD": 0,
        "TimeTakenToGuess_s": 5.735956,
        "Timestamp": "2024-11-23T15:41:40.82092+04:00",
        "TestType": "Contrast"
    },
    {
        "Username": null,
        "TrialNumber": 90,
        "EyeCondition": "Both",
        "CorrectOption": "D",
        "GuessedOption": "R",
        "LogMAR": 0.0,
        "Eccentricity_d": 0.0,
        "Theta_d": 0.0,
        "LetterSize_m": 0.0,
        "LogDVA": 0.0,
        "DVA": 0.0,
        "ContrastAlpha_rgb": 11.9445925,
        "Alpha1": 12.0,
        "Alpha2": 11.0,
        "Ratio": 0.94,
        "LogLum": 1.3293688598700211,
        "IPD": 0,
        "TimeTakenToGuess_s": 5.512945,
        "Timestamp": "2024-11-23T15:41:48.352932+04:00",
        "TestType": "Contrast"
    },
    {
        "Username": null,
        "TrialNumber": 91,
        "EyeCondition": "Left",
        "CorrectOption": "D",
        "GuessedOption": "R",
        "LogMAR": 0.0,
        "Eccentricity_d": 0.0,
        "Theta_d": 0.0,
        "LetterSize_m": 0.0,
        "LogDVA": 0.0,
        "DVA": 0.0,
        "ContrastAlpha_rgb": 13.4071407,
        "Alpha1": 14.0,
        "Alpha2": 13.0,
        "Ratio": 0.41,
        "LogLum": 1.2792039972334166,
        "IPD": 0,
        "TimeTakenToGuess_s": 3.84217,
        "Timestamp": "2024-11-23T15:41:56.121791+04:00",
        "TestType": "Contrast"
    },
    {
        "Username": null,
        "TrialNumber": 92,
        "EyeCondition": "Both",
        "CorrectOption": "Z",
        "GuessedOption": "Z",
        "LogMAR": 0.0,
        "Eccentricity_d": 0.0,
        "Theta_d": 0.0,
        "LetterSize_m": 0.0,
        "LogDVA": 0.0,
        "DVA": 0.0,
        "ContrastAlpha_rgb": 12.6547556,
        "Alpha1": 13.0,
        "Alpha2": 12.0,
        "Ratio": 0.65,
        "LogLum": 1.3042864285517188,
        "IPD": 0,
        "TimeTakenToGuess_s": 2.909496,
        "Timestamp": "2024-11-23T15:42:01.788134+04:00",
        "TestType": "Contrast"
    },
    {
        "Username": null,
        "TrialNumber": 93,
        "EyeCondition": "Left",
        "CorrectOption": "V",
        "GuessedOption": "V",
        "LogMAR": 0.0,
        "Eccentricity_d": 0.0,
        "Theta_d": 0.0,
        "LetterSize_m": 0.0,
        "LogDVA": 0.0,
        "DVA": 0.0,
        "ContrastAlpha_rgb": 14.20426,
        "Alpha1": 15.0,
        "Alpha2": 14.0,
        "Ratio": 0.2,
        "LogLum": 1.2541215659151144,
        "IPD": 0,
        "TimeTakenToGuess_s": 2.993338,
        "Timestamp": "2024-11-23T15:42:06.549368+04:00",
        "TestType": "Contrast"
    },
    {
        "Username": null,
        "TrialNumber": 94,
        "EyeCondition": "Left",
        "CorrectOption": "V",
        "GuessedOption": "V",
        "LogMAR": 0.0,
        "Eccentricity_d": 0.0,
        "Theta_d": 0.0,
        "LetterSize_m": 0.0,
        "LogDVA": 0.0,
        "DVA": 0.0,
        "ContrastAlpha_rgb": 13.4071407,
        "Alpha1": 14.0,
        "Alpha2": 13.0,
        "Ratio": 0.41,
        "LogLum": 1.2792039972334166,
        "IPD": 0,
        "TimeTakenToGuess_s": 2.812031,
        "Timestamp": "2024-11-23T15:42:11.533486+04:00",
        "TestType": "Contrast"
    },
    {
        "Username": null,
        "TrialNumber": 95,
        "EyeCondition": "Left",
        "CorrectOption": "C",
        "GuessedOption": "N",
        "LogMAR": 0.0,
        "Eccentricity_d": 0.0,
        "Theta_d": 0.0,
        "LetterSize_m": 0.0,
        "LogDVA": 0.0,
        "DVA": 0.0,
        "ContrastAlpha_rgb": 12.6547556,
        "Alpha1": 13.0,
        "Alpha2": 12.0,
        "Ratio": 0.65,
        "LogLum": 1.3042864285517188,
        "IPD": 0,
        "TimeTakenToGuess_s": 2.603367,
        "Timestamp": "2024-11-23T15:42:16.281133+04:00",
        "TestType": "Contrast"
    },
    {
        "Username": null,
        "TrialNumber": 96,
        "EyeCondition": "Right",
        "CorrectOption": "H",
        "GuessedOption": "N",
        "LogMAR": 0.0,
        "Eccentricity_d": 0.0,
        "Theta_d": 0.0,
        "LetterSize_m": 0.0,
        "LogDVA": 0.0,
        "DVA": 0.0,
        "ContrastAlpha_rgb": 14.20426,
        "Alpha1": 15.0,
        "Alpha2": 14.0,
        "Ratio": 0.2,
        "LogLum": 1.2541215659151139,
        "IPD": 0,
        "TimeTakenToGuess_s": 2.770344,
        "Timestamp": "2024-11-23T15:42:20.98681+04:00",
        "TestType": "Contrast"
    },
    {
        "Username": null,
        "TrialNumber": 97,
        "EyeCondition": "Right",
        "CorrectOption": "S",
        "GuessedOption": "R",
        "LogMAR": 0.0,
        "Eccentricity_d": 0.0,
        "Theta_d": 0.0,
        "LetterSize_m": 0.0,
        "LogDVA": 0.0,
        "DVA": 0.0,
        "ContrastAlpha_rgb": 15.0487719,
        "Alpha1": 16.0,
        "Alpha2": 15.0,
        "Ratio": 0.05,
        "LogLum": 1.2290391345968117,
        "IPD": 0,
        "TimeTakenToGuess_s": 3.786734,
        "Timestamp": "2024-11-23T15:42:25.915394+04:00",
        "TestType": "Contrast"
    },
    {
        "Username": null,
        "TrialNumber": 98,
        "EyeCondition": "Left",
        "CorrectOption": "N",
        "GuessedOption": "N",
        "LogMAR": 0.0,
        "Eccentricity_d": 0.0,
        "Theta_d": 0.0,
        "LetterSize_m": 0.0,
        "LogDVA": 0.0,
        "DVA": 0.0,
        "ContrastAlpha_rgb": 13.4071407,
        "Alpha1": 14.0,
        "Alpha2": 13.0,
        "Ratio": 0.41,
        "LogLum": 1.2792039972334166,
        "IPD": 0,
        "TimeTakenToGuess_s": 2.750812,
        "Timestamp": "2024-11-23T15:42:32.445078+04:00",
        "TestType": "Contrast"
    },
    {
        "Username": null,
        "TrialNumber": 99,
        "EyeCondition": "Left",
        "CorrectOption": "R",
        "GuessedOption": "N",
        "LogMAR": 0.0,
        "Eccentricity_d": 0.0,
        "Theta_d": 0.0,
        "LetterSize_m": 0.0,
        "LogDVA": 0.0,
        "DVA": 0.0,
        "ContrastAlpha_rgb": 12.6547556,
        "Alpha1": 13.0,
        "Alpha2": 12.0,
        "Ratio": 0.65,
        "LogLum": 1.3042864285517188,
        "IPD": 0,
        "TimeTakenToGuess_s": 2.993254,
        "Timestamp": "2024-11-23T15:42:37.520982+04:00",
        "TestType": "Contrast"
    },
    {
        "Username": null,
        "TrialNumber": 100,
        "EyeCondition": "Right",
        "CorrectOption": "N",
        "GuessedOption": "N",
        "LogMAR": 0.0,
        "Eccentricity_d": 0.0,
        "Theta_d": 0.0,
        "LetterSize_m": 0.0,
        "LogDVA": 0.0,
        "DVA": 0.0,
        "ContrastAlpha_rgb": 15.9434929,
        "Alpha1": 16.0,
        "Alpha2": 15.0,
        "Ratio": 0.94,
        "LogLum": 1.2039567032785095,
        "IPD": 0,
        "TimeTakenToGuess_s": 2.449955,
        "Timestamp": "2024-11-23T15:42:42.588863+04:00",
        "TestType": "Contrast"
    },
    {
        "Username": null,
        "TrialNumber": 101,
        "EyeCondition": "Both",
        "CorrectOption": "C",
        "GuessedOption": "V",
        "LogMAR": 0.0,
        "Eccentricity_d": 0.0,
        "Theta_d": 0.0,
        "LetterSize_m": 0.0,
        "LogDVA": 0.0,
        "DVA": 0.0,
        "ContrastAlpha_rgb": 11.9445925,
        "Alpha1": 12.0,
        "Alpha2": 11.0,
        "Ratio": 0.94,
        "LogLum": 1.3293688598700211,
        "IPD": 0,
        "TimeTakenToGuess_s": 3.118291,
        "Timestamp": "2024-11-23T15:42:47.197199+04:00",
        "TestType": "Contrast"
    },
    {
        "Username": null,
        "TrialNumber": 102,
        "EyeCondition": "Left",
        "CorrectOption": "O",
        "GuessedOption": "H",
        "LogMAR": 0.0,
        "Eccentricity_d": 0.0,
        "Theta_d": 0.0,
        "LetterSize_m": 0.0,
        "LogDVA": 0.0,
        "DVA": 0.0,
        "ContrastAlpha_rgb": 13.4071407,
        "Alpha1": 14.0,
        "Alpha2": 13.0,
        "Ratio": 0.41,
        "LogLum": 1.2792039972334166,
        "IPD": 0,
        "TimeTakenToGuess_s": 2.839904,
        "Timestamp": "2024-11-23T15:42:52.139725+04:00",
        "TestType": "Contrast"
    },
    {
        "Username": null,
        "TrialNumber": 103,
        "EyeCondition": "Left",
        "CorrectOption": "R",
        "GuessedOption": "R",
        "LogMAR": 0.0,
        "Eccentricity_d": 0.0,
        "Theta_d": 0.0,
        "LetterSize_m": 0.0,
        "LogDVA": 0.0,
        "DVA": 0.0,
        "ContrastAlpha_rgb": 13.7999468,
        "Alpha1": 14.0,
        "Alpha2": 13.0,
        "Ratio": 0.8,
        "LogLum": 1.2666627815742655,
        "IPD": 0,
        "TimeTakenToGuess_s": 3.257641,
        "Timestamp": "2024-11-23T15:42:57.443954+04:00",
        "TestType": "Contrast"
    },
    {
        "Username": null,
        "TrialNumber": 104,
        "EyeCondition": "Left",
        "CorrectOption": "K",
        "GuessedOption": "H",
        "LogMAR": 0.0,
        "Eccentricity_d": 0.0,
        "Theta_d": 0.0,
        "LetterSize_m": 0.0,
        "LogDVA": 0.0,
        "DVA": 0.0,
        "ContrastAlpha_rgb": 13.4071407,
        "Alpha1": 14.0,
        "Alpha2": 13.0,
        "Ratio": 0.41,
        "LogLum": 1.2792039972334166,
        "IPD": 0,
        "TimeTakenToGuess_s": 3.257491,
        "Timestamp": "2024-11-23T15:43:02.734676+04:00",
        "TestType": "Contrast"
    },
    {
        "Username": null,
        "TrialNumber": 105,
        "EyeCondition": "Both",
        "CorrectOption": "Z",
        "GuessedOption": "N",
        "LogMAR": 0.0,
        "Eccentricity_d": 0.0,
        "Theta_d": 0.0,
        "LetterSize_m": 0.0,
        "LogDVA": 0.0,
        "DVA": 0.0,
        "ContrastAlpha_rgb": 12.6547556,
        "Alpha1": 13.0,
        "Alpha2": 12.0,
        "Ratio": 0.65,
        "LogLum": 1.3042864285517188,
        "IPD": 0,
        "TimeTakenToGuess_s": 3.048625,
        "Timestamp": "2024-11-23T15:43:08.387039+04:00",
        "TestType": "Contrast"
    },
    {
        "Username": null,
        "TrialNumber": 106,
        "EyeCondition": "Both",
        "CorrectOption": "H",
        "GuessedOption": "H",
        "LogMAR": 0.0,
        "Eccentricity_d": 0.0,
        "Theta_d": 0.0,
        "LetterSize_m": 0.0,
        "LogDVA": 0.0,
        "DVA": 0.0,
        "ContrastAlpha_rgb": 13.0255165,
        "Alpha1": 14.0,
        "Alpha2": 13.0,
        "Ratio": 0.03,
        "LogLum": 1.2917452128925677,
        "IPD": 0,
        "TimeTakenToGuess_s": 2.784398,
        "Timestamp": "2024-11-23T15:43:13.259714+04:00",
        "TestType": "Contrast"
    },
    {
        "Username": null,
        "TrialNumber": 107,
        "EyeCondition": "Right",
        "CorrectOption": "V",
        "GuessedOption": "V",
        "LogMAR": 0.0,
        "Eccentricity_d": 0.0,
        "Theta_d": 0.0,
        "LetterSize_m": 0.0,
        "LogDVA": 0.0,
        "DVA": 0.0,
        "ContrastAlpha_rgb": 15.0487719,
        "Alpha1": 16.0,
        "Alpha2": 15.0,
        "Ratio": 0.05,
        "LogLum": 1.2290391345968117,
        "IPD": 0,
        "TimeTakenToGuess_s": 2.714442,
        "Timestamp": "2024-11-23T15:43:18.132445+04:00",
        "TestType": "Contrast"
    },
    {
        "Username": null,
        "TrialNumber": 108,
        "EyeCondition": "Both",
        "CorrectOption": "K",
        "GuessedOption": "N",
        "LogMAR": 0.0,
        "Eccentricity_d": 0.0,
        "Theta_d": 0.0,
        "LetterSize_m": 0.0,
        "LogDVA": 0.0,
        "DVA": 0.0,
        "ContrastAlpha_rgb": 12.6547556,
        "Alpha1": 13.0,
        "Alpha2": 12.0,
        "Ratio": 0.65,
        "LogLum": 1.3042864285517188,
        "IPD": 0,
        "TimeTakenToGuess_s": 3.675328,
        "Timestamp": "2024-11-23T15:43:22.713166+04:00",
        "TestType": "Contrast"
    },
    {
        "Username": null,
        "TrialNumber": 109,
        "EyeCondition": "Right",
        "CorrectOption": "D",
        "GuessedOption": "C",
        "LogMAR": 0.0,
        "Eccentricity_d": 0.0,
        "Theta_d": 0.0,
        "LetterSize_m": 0.0,
        "LogDVA": 0.0,
        "DVA": 0.0,
        "ContrastAlpha_rgb": 14.20426,
        "Alpha1": 15.0,
        "Alpha2": 14.0,
        "Ratio": 0.2,
        "LogLum": 1.2541215659151139,
        "IPD": 0,
        "TimeTakenToGuess_s": 2.811921,
        "Timestamp": "2024-11-23T15:43:28.74152+04:00",
        "TestType": "Contrast"
    },
    {
        "Username": null,
        "TrialNumber": 110,
        "EyeCondition": "Both",
        "CorrectOption": "H",
        "GuessedOption": "N",
        "LogMAR": 0.0,
        "Eccentricity_d": 0.0,
        "Theta_d": 0.0,
        "LetterSize_m": 0.0,
        "LogDVA": 0.0,
        "DVA": 0.0,
        "ContrastAlpha_rgb": 13.0255165,
        "Alpha1": 14.0,
        "Alpha2": 13.0,
        "Ratio": 0.03,
        "LogLum": 1.2917452128925677,
        "IPD": 0,
        "TimeTakenToGuess_s": 2.853676,
        "Timestamp": "2024-11-23T15:43:34.268731+04:00",
        "TestType": "Contrast"
    },
    {
        "Username": null,
        "TrialNumber": 111,
        "EyeCondition": "Both",
        "CorrectOption": "N",
        "GuessedOption": "N",
        "LogMAR": 0.0,
        "Eccentricity_d": 0.0,
        "Theta_d": 0.0,
        "LetterSize_m": 0.0,
        "LogDVA": 0.0,
        "DVA": 0.0,
        "ContrastAlpha_rgb": 13.4071407,
        "Alpha1": 14.0,
        "Alpha2": 13.0,
        "Ratio": 0.41,
        "LogLum": 1.2792039972334166,
        "IPD": 0,
        "TimeTakenToGuess_s": 3.034696,
        "Timestamp": "2024-11-23T15:43:39.266642+04:00",
        "TestType": "Contrast"
    },
    {
        "Username": null,
        "TrialNumber": 112,
        "EyeCondition": "Right",
        "CorrectOption": "H",
        "GuessedOption": "H",
        "LogMAR": 0.0,
        "Eccentricity_d": 0.0,
        "Theta_d": 0.0,
        "LetterSize_m": 0.0,
        "LogDVA": 0.0,
        "DVA": 0.0,
        "ContrastAlpha_rgb": 15.0487719,
        "Alpha1": 16.0,
        "Alpha2": 15.0,
        "Ratio": 0.05,
        "LogLum": 1.2290391345968117,
        "IPD": 0,
        "TimeTakenToGuess_s": 2.742205,
        "Timestamp": "2024-11-23T15:43:44.821751+04:00",
        "TestType": "Contrast"
    },
    {
        "Username": null,
        "TrialNumber": 113,
        "EyeCondition": "Both",
        "CorrectOption": "S",
        "GuessedOption": "O",
        "LogMAR": 0.0,
        "Eccentricity_d": 0.0,
        "Theta_d": 0.0,
        "LetterSize_m": 0.0,
        "LogDVA": 0.0,
        "DVA": 0.0,
        "ContrastAlpha_rgb": 13.0255165,
        "Alpha1": 14.0,
        "Alpha2": 13.0,
        "Ratio": 0.03,
        "LogLum": 1.2917452128925677,
        "IPD": 0,
        "TimeTakenToGuess_s": 3.842174,
        "Timestamp": "2024-11-23T15:43:49.513659+04:00",
        "TestType": "Contrast"
    },
    {
        "Username": null,
        "TrialNumber": 114,
        "EyeCondition": "Both",
        "CorrectOption": "S",
        "GuessedOption": "S",
        "LogMAR": 0.0,
        "Eccentricity_d": 0.0,
        "Theta_d": 0.0,
        "LetterSize_m": 0.0,
        "LogDVA": 0.0,
        "DVA": 0.0,
        "ContrastAlpha_rgb": 13.4071407,
        "Alpha1": 14.0,
        "Alpha2": 13.0,
        "Ratio": 0.41,
        "LogLum": 1.2792039972334166,
        "IPD": 0,
        "TimeTakenToGuess_s": 2.81207,
        "Timestamp": "2024-11-23T15:43:55.151924+04:00",
        "TestType": "Contrast"
    },
    {
        "Username": null,
        "TrialNumber": 115,
        "EyeCondition": "Left",
        "CorrectOption": "K",
        "GuessedOption": "H",
        "LogMAR": 0.0,
        "Eccentricity_d": 0.0,
        "Theta_d": 0.0,
        "LetterSize_m": 0.0,
        "LogDVA": 0.0,
        "DVA": 0.0,
        "ContrastAlpha_rgb": 13.7999468,
        "Alpha1": 14.0,
        "Alpha2": 13.0,
        "Ratio": 0.8,
        "LogLum": 1.2666627815742655,
        "IPD": 0,
        "TimeTakenToGuess_s": 2.714383,
        "Timestamp": "2024-11-23T15:44:00.581809+04:00",
        "TestType": "Contrast"
    },
    {
        "Username": null,
        "TrialNumber": 116,
        "EyeCondition": "Left",
        "CorrectOption": "V",
        "GuessedOption": "V",
        "LogMAR": 0.0,
        "Eccentricity_d": 0.0,
        "Theta_d": 0.0,
        "LetterSize_m": 0.0,
        "LogDVA": 0.0,
        "DVA": 0.0,
        "ContrastAlpha_rgb": 14.20426,
        "Alpha1": 15.0,
        "Alpha2": 14.0,
        "Ratio": 0.2,
        "LogLum": 1.2541215659151144,
        "IPD": 0,
        "TimeTakenToGuess_s": 2.923264,
        "Timestamp": "2024-11-23T15:44:05.440693+04:00",
        "TestType": "Contrast"
    },
    {
        "Username": null,
        "TrialNumber": 117,
        "EyeCondition": "Both",
        "CorrectOption": "R",
        "GuessedOption": "R",
        "LogMAR": 0.0,
        "Eccentricity_d": 0.0,
        "Theta_d": 0.0,
        "LetterSize_m": 0.0,
        "LogDVA": 0.0,
        "DVA": 0.0,
        "ContrastAlpha_rgb": 13.0255165,
        "Alpha1": 14.0,
        "Alpha2": 13.0,
        "Ratio": 0.03,
        "LogLum": 1.2917452128925677,
        "IPD": 0,
        "TimeTakenToGuess_s": 2.756174,
        "Timestamp": "2024-11-23T15:44:10.118759+04:00",
        "TestType": "Contrast"
    },
    {
        "Username": null,
        "TrialNumber": 118,
        "EyeCondition": "Right",
        "CorrectOption": "Z",
        "GuessedOption": "N",
        "LogMAR": 0.0,
        "Eccentricity_d": 0.0,
        "Theta_d": 0.0,
        "LetterSize_m": 0.0,
        "LogDVA": 0.0,
        "DVA": 0.0,
        "ContrastAlpha_rgb": 14.6204195,
        "Alpha1": 15.0,
        "Alpha2": 14.0,
        "Ratio": 0.62,
        "LogLum": 1.2415803502559628,
        "IPD": 0,
        "TimeTakenToGuess_s": 2.881534,
        "Timestamp": "2024-11-23T15:44:14.963531+04:00",
        "TestType": "Contrast"
    },
    {
        "Username": null,
        "TrialNumber": 119,
        "EyeCondition": "Right",
        "CorrectOption": "R",
        "GuessedOption": "N",
        "LogMAR": 0.0,
        "Eccentricity_d": 0.0,
        "Theta_d": 0.0,
        "LetterSize_m": 0.0,
        "LogDVA": 0.0,
        "DVA": 0.0,
        "ContrastAlpha_rgb": 15.0487719,
        "Alpha1": 16.0,
        "Alpha2": 15.0,
        "Ratio": 0.05,
        "LogLum": 1.2290391345968117,
        "IPD": 0,
        "TimeTakenToGuess_s": 2.867744,
        "Timestamp": "2024-11-23T15:44:19.864114+04:00",
        "TestType": "Contrast"
    },
    {
        "Username": null,
        "TrialNumber": 120,
        "EyeCondition": "Left",
        "CorrectOption": "K",
        "GuessedOption": "N",
        "LogMAR": 0.0,
        "Eccentricity_d": 0.0,
        "Theta_d": 0.0,
        "LetterSize_m": 0.0,
        "LogDVA": 0.0,
        "DVA": 0.0,
        "ContrastAlpha_rgb": 13.7999468,
        "Alpha1": 14.0,
        "Alpha2": 13.0,
        "Ratio": 0.8,
        "LogLum": 1.2666627815742655,
        "IPD": 0,
        "TimeTakenToGuess_s": 2.63097,
        "Timestamp": "2024-11-23T15:44:24.778801+04:00",
        "TestType": "Contrast"
    }
]